src/hcaptcha-solver/__init__.py
src/hcaptcha-solver/captcha_handler.py
src/hcaptcha-solver/captcha_wd_handler.py
src/hcaptcha-solver/nn_handler.py
hcaptchahandler-0.1.2.dist-info/METADATA
hcaptchahandler-0.1.2.dist-info/WHEEL
hcaptchahandler-0.1.2.dist-info/licenses/LICENSE
hcaptchahandler-0.1.2.dist-info/RECORD
