Metadata-Version: 2.1
Name: hcaptchahandler
Version: 0.1.2
Summary: Selenium hCaptcha Solver
Project-URL: GitHub, https://github.com/xTerradon/hcaptcha-solver.git
Author: Terradon
License-File: LICENSE
Classifier: License :: OSI Approved :: MIT License
Classifier: Operating System :: OS Independent
Classifier: Programming Language :: Python :: 3
Requires-Python: >=3.7
